jac_cloud/__init__.py
jac_cloud/core/__init__.py
jac_cloud/core/archetype.py
jac_cloud/core/context.py
jac_cloud/core/memory.py
jac_cloud/core/tests/test_archetype.jac
jac_cloud/jaseci/__init__.py
jac_cloud/jaseci/datasources/__init__.py
jac_cloud/jaseci/datasources/collection.py
jac_cloud/jaseci/datasources/localdb.py
jac_cloud/jaseci/datasources/redis.py
jac_cloud/jaseci/dtos/__init__.py
jac_cloud/jaseci/dtos/sso.py
jac_cloud/jaseci/dtos/user.py
jac_cloud/jaseci/dtos/webhook.py
jac_cloud/jaseci/dtos/websocket.py
jac_cloud/jaseci/main.py
jac_cloud/jaseci/models/__init__.py
jac_cloud/jaseci/models/user.py
jac_cloud/jaseci/models/webhook.py
jac_cloud/jaseci/routers/__init__.py
jac_cloud/jaseci/routers/healthz.py
jac_cloud/jaseci/routers/sso.py
jac_cloud/jaseci/routers/user.py
jac_cloud/jaseci/routers/utils.py
jac_cloud/jaseci/routers/webhook.py
jac_cloud/jaseci/security/__init__.py
jac_cloud/jaseci/sso/__init__.py
jac_cloud/jaseci/sso/apple.py
jac_cloud/jaseci/sso/google.py
jac_cloud/jaseci/utils/__init__.py
jac_cloud/jaseci/utils/logger.py
jac_cloud/jaseci/utils/mail.py
jac_cloud/plugin/__init__.py
jac_cloud/plugin/cli.py
jac_cloud/plugin/implementation/__init__.py
jac_cloud/plugin/implementation/api.py
jac_cloud/plugin/implementation/scheduler.py
jac_cloud/plugin/implementation/websocket.py
jac_cloud/plugin/jaseci.py
jac_cloud/runner.py
jac_cloud/standalone.py
jac_cloud/tests/__init__.py
jac_cloud/tests/clean_openapi_specs.yaml
jac_cloud/tests/fixtures/jac_run_serve.jac
jac_cloud/tests/localhost.crt
jac_cloud/tests/localhost.key
jac_cloud/tests/openapi_specs.yaml
jac_cloud/tests/simple.json
jac_cloud/tests/simple_graph.jac
jac_cloud/tests/test_cli.py
jac_cloud/tests/test_hot_reload.py
jac_cloud/tests/test_simple_graph.py
jac_cloud/tests/test_ssl_service.py
jac_cloud/tests/test_utils.py
jac_cloud/tests/websocket.jac
jac_cloud-0.2.11.dist-info/METADATA
jac_cloud-0.2.11.dist-info/WHEEL
jac_cloud-0.2.11.dist-info/entry_points.txt
jac_cloud-0.2.11.dist-info/RECORD
